setuptools_cmake_helper/__init__.py
setuptools_cmake_helper/version.py
setuptools_cmake_helper-0.2.1.dist-info/licenses/LICENSE
setuptools_cmake_helper-0.2.1.dist-info/METADATA
setuptools_cmake_helper-0.2.1.dist-info/WHEEL
setuptools_cmake_helper-0.2.1.dist-info/top_level.txt
setuptools_cmake_helper-0.2.1.dist-info/RECORD
