Metadata-Version: 2.4
Name: setuptools-cmake-helper
Version: 0.2.1
Summary: Simpler helper to build a Python C/C++ Extension using CMake
Author: Henrique Gemignani Passos Lima
License-Expression: Apache-2.0
Project-URL: Homepage, https://github.com/henriquegemignani/setuptools-cmake-helper
Classifier: Development Status :: 3 - Alpha
Classifier: Intended Audience :: Developers
Classifier: Programming Language :: Python :: 3.9
Classifier: Programming Language :: Python :: 3.10
Classifier: Programming Language :: Python :: 3.11
Classifier: Programming Language :: Python :: 3.12
Classifier: Programming Language :: Python :: 3.13
Classifier: Programming Language :: Python :: 3.14
Requires-Python: >=3.9
License-File: LICENSE
Requires-Dist: setuptools
Provides-Extra: cython
Requires-Dist: Cython; extra == "cython"
Provides-Extra: test
Requires-Dist: pytest; extra == "test"
Requires-Dist: pytest-cov; extra == "test"
Requires-Dist: build; extra == "test"
Requires-Dist: wheel; extra == "test"
Dynamic: license-file
